[
  {
    "n": "인터넷 복권판매사이트",
    "a": "서울특별시 서초구 남부순환로 2423 (서초동, 한원빌딩) 4층",
    "lat": 37.481793,
    "lng": 127.015371,
    "w": 105
  },
  {
    "n": "25시슈퍼",
    "a": "함송로14번길 13-17",
    "lat": 37.3624626201338,
    "lng": 126.729984027881,
    "w": 8
  },
  {
    "n": "복권판매점",
    "a": "동탄중심상가2길 37 1층으",
    "lat": 37.2065291995327,
    "lng": 127.073064595643,
    "w": 7
  },
  {
    "n": "NBA(엔비에이)",
    "a": "운서동 2803-1 128호",
    "lat": 37.4934353770054,
    "lng": 126.49149218543,
    "w": 6
  },
  {
    "n": "헬로마트",
    "a": "서울 도봉구 도봉2동 89-148",
    "lat": 37.6803097592264,
    "lng": 127.045967923281,
    "w": 5
  },
  {
    "n": "북문복권방",
    "a": "정조로 927-1",
    "lat": 37.2902970908823,
    "lng": 127.012826577136,
    "w": 5
  },
  {
    "n": "로또",
    "a": "서울 중구 신당동 133-14",
    "lat": 37.5637869159653,
    "lng": 127.01942735357,
    "w": 5
  },
  {
    "n": "데이앤나잇",
    "a": "서울 성북구 종암동 132 종암우림카이저팰리스 1층 101호",
    "lat": 37.6019639910993,
    "lng": 127.03348913167,
    "w": 5
  },
  {
    "n": "초월대박복권방",
    "a": "경기 광주시 초월읍 대쌍령리 196-18",
    "lat": 37.3866858786882,
    "lng": 127.288230808256,
    "w": 5
  }
]